bunny_cdk/__init__.py
bunny_cdk/py.typed
bunny_cdk/_jsii/__init__.py
bunny_cdk/_jsii/bunny-cdk@0.0.5.jsii.tgz
bunny_cdk-0.0.5.dist-info/LICENSE
bunny_cdk-0.0.5.dist-info/METADATA
bunny_cdk-0.0.5.dist-info/WHEEL
bunny_cdk-0.0.5.dist-info/top_level.txt
bunny_cdk-0.0.5.dist-info/RECORD
