Metadata-Version: 2.1
Name: bunny-cdk
Version: 0.0.5
Summary: bunny-cdk
Home-page: https://bunny-launcher.net/bunny-cdk/quickstart/
Author: John L. Armstrong IV<20903247+jlarmstrongiv@users.noreply.github.com>
License: AGPL-3.0-or-later
Project-URL: Source, https://github.com/jlarmstrongiv/bunny-cdk.git
Classifier: Intended Audience :: Developers
Classifier: Operating System :: OS Independent
Classifier: Programming Language :: JavaScript
Classifier: Programming Language :: Python :: 3 :: Only
Classifier: Programming Language :: Python :: 3.8
Classifier: Programming Language :: Python :: 3.9
Classifier: Programming Language :: Python :: 3.10
Classifier: Programming Language :: Python :: 3.11
Classifier: Typing :: Typed
Classifier: Development Status :: 5 - Production/Stable
Classifier: License :: OSI Approved
Requires-Python: ~=3.8
License-File: LICENSE
Requires-Dist: aws-cdk-lib<3.0.0,>=2.1.0
Requires-Dist: constructs<11.0.0,>=10.0.5
Requires-Dist: jsii<2.0.0,>=1.105.0
Requires-Dist: publication>=0.0.3
Requires-Dist: typeguard<4.3.0,>=2.13.3
